trex/__init__.py
trex/client/trex_async_client.py
trex/client/trex_port.py
trex/client/trex_root_path.py
trex/client/trex_stateless_client.py
trex/client/__init__.py
trex/client/trex_client.py
trex/client/outer_packages.py
trex/client/trex_adv_client.py
trex/common/trex_status_e.py
trex/common/trex_status.py
trex/common/trex_stl_exceptions.py
trex/common/trex_exceptions.py
trex/common/__init__.py
trex/common/trex_stats.py
trex/common/trex_types.py
trex/common/trex_streams.py
trex/common/external_packages.py
trex/common/text_opts.py
trex/console/trex_root_path.py
trex/console/trex_console.py
trex/console/__init__.py
trex/console/trex_tui.py
trex/client_utils/packet_builder.py
trex/client_utils/packet_builder_interface.py
trex/client_utils/parsing_opts.py
trex/client_utils/yaml_utils.py
trex/client_utils/trex_yaml_gen.py
trex/client_utils/scapy_packet_builder.py
trex/client_utils/__init__.py
trex/client_utils/text_tables.py
trex/client_utils/jsonrpc_client.py
trex/client_utils/general_utils.py
trex/client_utils/external_packages.py
trex/server/trex_daemon_server.py
trex/server/zmq_monitor_thread.py
trex/server/trex_launch_thread.py
trex/server/outer_packages.py
trex/server/extended_daemon_runner.py
trex/server/CCustomLogger.py
trex/server/trex_server.py
trex_api-0.0.2.dist-info/metadata.json
trex_api-0.0.2.dist-info/top_level.txt
trex_api-0.0.2.dist-info/DESCRIPTION.rst
trex_api-0.0.2.dist-info/RECORD
trex_api-0.0.2.dist-info/WHEEL
trex_api-0.0.2.dist-info/METADATA
