Metadata-Version: 2.0
Name: trex-api
Version: 0.0.2
Summary: module for trex API
Home-page: https://github.com/RaminNietzsche/trex
Author: Ramin Najjarbashi
Author-email: Y21GdGFXNHVibUZxWVhKaVlYTm9hVUJuYldGcGJDNWpiMjA9
License: GPL-3
Platform: any
Classifier: Operating System :: OS Independent
Classifier: Programming Language :: Python :: 2.7
Requires-Dist: enum34 (>=1.1.3)
Requires-Dist: jsonrpclib-pelix (>=0.2.6)
Requires-Dist: texttable (>=0.8.4)
Requires-Dist: pyyaml (>=3.11)
Requires-Dist: pyzmq (>=14.0.1)
Requires-Dist: dpkt (>=1.8.7)
